yaddy/__init__.py
yaddy/domain_object.py
yaddy/entity.py
yaddy/value.py
yaddy-0.1.1.dist-info/entry_points.txt
yaddy-0.1.1.dist-info/LICENSE
yaddy-0.1.1.dist-info/WHEEL
yaddy-0.1.1.dist-info/METADATA
yaddy-0.1.1.dist-info/RECORD
